fuelfinder/__init__.py
fuelfinder-0.1.3.dist-info/METADATA
fuelfinder-0.1.3.dist-info/WHEEL
fuelfinder-0.1.3.dist-info/entry_points.txt
fuelfinder-0.1.3.dist-info/licenses/LICENSE
fuelfinder-0.1.3.dist-info/RECORD
