Metadata-Version: 2.3
Name: fuelfinder
Version: 0.1.3
Summary: Add your description here
Author-email: Jakob Guldberg Aaes <jakob1379@gmail.com>
Requires-Python: >=3.12
Requires-Dist: bs4>=0.0.2
Requires-Dist: diskcache>=5.6.3
Requires-Dist: pandas>=2.1.4
Requires-Dist: requests>=2.32.3
Requires-Dist: sane-rich-logging>=1.0.1
Requires-Dist: typer>=0.14.0
